WitMessagesPackage/__init__.py
WitMessagesPackage/phoneNumber.py
WitMessagesPackage/sengridClass.py
WitMessagesPackage/sms.py
WitMessagesPackage/whatsApp.py
WitMessagesPackage-0.0.2.dist-info/LICENSE
WitMessagesPackage-0.0.2.dist-info/METADATA
WitMessagesPackage-0.0.2.dist-info/WHEEL
WitMessagesPackage-0.0.2.dist-info/top_level.txt
WitMessagesPackage-0.0.2.dist-info/RECORD
