Metadata-Version: 2.1
Name: WitMessagesPackage
Version: 0.0.2
Summary: This repository will generate an interface to send emails, sms and WhatsApp to different companies
Home-page: https://github.com/ferdelcorro/WitMessagesPackage
Author: Fernando del Corro
Author-email: ferdelcorro@gmail.com
License: UNKNOWN
Platform: UNKNOWN
Classifier: Programming Language :: Python :: 3
Classifier: License :: OSI Approved :: MIT License
Classifier: Operating System :: OS Independent
Requires-Python: >=3.6
Requires-Dist: phonenumbers (==8.12.1)
Requires-Dist: requests (==2.23.0)
Requires-Dist: sendgrid (==6.1.3)
